{"unusual": false, "description": "Knuten hand, fram\u00e5triktad och ned\u00e5tv\u00e4nd, f\u00f6rs ned till kontakt ovanp\u00e5 knutna handen, h\u00f6gerriktad och in\u00e5tv\u00e4nd, f\u00f6rs slutligen upp\u00e5t och \u00e5t h\u00f6ger samtidigt som den vrids \u00e5t v\u00e4nster", "video_url": "http://130.237.171.78/T11897.mov", "versions": [{"description": "Knuten hand, fram\u00e5triktad och ned\u00e5tv\u00e4nd, f\u00f6rs ned till kontakt ovanp\u00e5 flata handen, h\u00f6gerriktad och upp\u00e5tv\u00e4nd, f\u00f6rs slutligen upp\u00e5t och \u00e5t h\u00f6ger samtidigt som den vrids \u00e5t v\u00e4nster", "video_url": "http://130.237.171.78/V11897a.mov", "id": "V11897a"}, {"description": "Knuten hand, fram\u00e5triktad och ned\u00e5tv\u00e4nd, f\u00f6rs f\u00f6rst ned\u00e5t, f\u00f6rs slutligen upp\u00e5t och \u00e5t h\u00f6ger samtidigt som den vrids \u00e5t v\u00e4nster", "video_url": "http://130.237.171.78/V11897b.mov", "id": "V11897b"}], "deleted": false, "tags": [{"tag": "Siffror - grundtal", "id": 35}], "updated_at": "2012-03-15T23:00:00Z", "snapshots": [], "ref_id": "11897", "examples": [{"description": "A: Hemma har jag en datask\u00e4rm som \u00e4r 19 tum.", "video_url": "http://130.237.171.78/M11897a.mov", "id": "M11897a"}, {"description": "B: Telefonnumret till Taxi Stockholm \u00e4r 08 19 19 19.", "video_url": "http://130.237.171.78/M11897b.mov", "id": "M11897b"}], "words": [{"word": "nitton", "id": 7317}, {"word": "19", "id": 7318}], "id": 6498}