{"unusual": false, "description": "Sprethanden, upp\u00e5triktad och v\u00e4nsterv\u00e4nd, kontakt med pannan, f\u00f6rs sedan fram\u00e5t med spelande fingrar, upprepas", "video_url": "http://130.237.171.78/T00796.mov", "versions": [], "deleted": false, "tags": [], "updated_at": "2012-03-15T23:00:00Z", "snapshots": [], "ref_id": "796", "examples": [{"description": "A: Ig\u00e5r drack jag tv\u00e5 glas vin och blev lite l\u00e4tt berusad.", "video_url": "http://130.237.171.78/M00796a.mov", "id": "M00796a"}], "words": [{"word": "l\u00e4tt berusad", "id": 902}], "id": 703}