{"unusual": false, "description": "A-handen, v\u00e4nsterriktad och in\u00e5tv\u00e4nd, kontakt med v\u00e4nstra sidan av br\u00f6stet, f\u00f6rs \u00e5t h\u00f6ger, kontakt", "video_url": "http://130.237.171.78/T01274.mov", "versions": [], "deleted": false, "tags": [], "updated_at": "2012-03-15T23:00:00Z", "snapshots": [], "ref_id": "1274", "examples": [{"description": "A: Min dotter blir snart myndig.", "video_url": "http://130.237.171.78/M01274a.mov", "id": "M01274a"}], "words": [{"word": "myndig", "id": 1338}], "id": 1072}