{"unusual": false, "description": "A-h\u00e4nder, v\u00e4nda mot varandra, den h\u00f6gra upp\u00e5triktad, och den v\u00e4nstra fram\u00e5triktad, f\u00f6rs fram\u00e5t med bibeh\u00e5llen kontakt bredvid varandra samtidigt som de sl\u00e5s fram och upp ett par g\u00e5nger", "video_url": "http://130.237.171.78/T01344.mov", "versions": [], "deleted": false, "tags": [], "updated_at": "2012-03-15T23:00:00Z", "snapshots": [], "ref_id": "1344", "examples": [], "words": [{"word": "formulera", "id": 1413}, {"word": "formulering", "id": 1414}], "id": 1131}