{"unusual": false, "description": "Klohanden, fram\u00e5triktad och v\u00e4nsterv\u00e4nd, f\u00f6rs ned\u00e5t samtidigt som den f\u00f6r\u00e4ndras till knuten hand till kontakt ovanp\u00e5 flata handen, h\u00f6gerriktad och upp\u00e5tv\u00e4nd", "video_url": "http://130.237.171.78/T01591.mov", "versions": [], "deleted": false, "tags": [], "updated_at": "2012-03-25T22:00:00Z", "snapshots": [], "ref_id": "1591", "examples": [{"description": "A: Jag hade inte pluggat inf\u00f6r provet s\u00e5 n\u00e4r jag s\u00e5g fr\u00e5gorna hade jag ingen chans att besvara dem.", "video_url": "http://130.237.171.78/M01591a.mov", "id": "M01591a"}, {"description": "B: D\u00f6rren var l\u00e5st s\u00e5 jag hade ingen m\u00f6jlighet att komma in.", "video_url": "http://130.237.171.78/M01591b.mov", "id": "M01591b"}], "words": [{"word": "chansl\u00f6s", "id": 1627}, {"word": "hj\u00e4lpl\u00f6s", "id": 1628}, {"word": "st\u00e4lld", "id": 1629}], "id": 1314}