{"unusual": false, "description": "O-handen, upp\u00e5triktad och fram\u00e5tv\u00e4nd, f\u00f6rs fram\u00e5t och ned\u00e5t samtidigt som den sl\u00e5s fram\u00e5t och f\u00f6r\u00e4ndras till sprethand", "video_url": "http://130.237.171.78/T01784.mov", "versions": [], "deleted": false, "tags": [], "updated_at": "2012-03-22T23:00:00Z", "snapshots": [], "ref_id": "1784", "examples": [{"description": "A: Jag har en massa skr\u00e4p p\u00e5 vinden. Jag m\u00e5ste rensa och kasta grejer.", "video_url": "http://130.237.171.78/M01784a.mov", "id": "M01784a"}], "words": [{"word": "kasta", "id": 1785}, {"word": "sl\u00e4nga", "id": 1786}], "id": 1445}