{"unusual": false, "description": "Knutna handen, ned\u00e5triktad och v\u00e4nsterv\u00e4nd, f\u00f6rs kort ned\u00e5t, upprepas", "video_url": "http://130.237.171.78/T02037.mov", "versions": [], "deleted": false, "tags": [], "updated_at": "2012-03-15T23:00:00Z", "snapshots": [], "ref_id": "2037", "examples": [{"description": "A: Jag har flera olika sorters v\u00e4skor hemma. Ska jag tr\u00e4na tar jag en liten v\u00e4ska medan jag tar en riktigt stor n\u00e4r jag ska resa bort.", "video_url": "http://130.237.171.78/M02037a.mov", "id": "M02037a"}], "words": [{"word": "v\u00e4ska", "id": 1990}], "id": 1619}