{"unusual": false, "description": "Stora nyphanden, v\u00e4nsterriktad och in\u00e5tv\u00e4nd, kontakt med hakan, f\u00f6rs ned\u00e5t och fram\u00e5t samtidigt som den vrids ned\u00e5t och f\u00f6r\u00e4ndras till sprethand", "video_url": "http://130.237.171.78/T04545.mov", "versions": [], "deleted": false, "tags": [], "updated_at": "2012-03-15T23:00:00Z", "snapshots": [], "ref_id": "4545", "examples": [{"description": "A: N\u00e5gra av mina sl\u00e4ktingar har reumatism. Risken finns att jag ocks\u00e5 f\u00e5r det men jag hoppas att jag slipper.", "video_url": "http://130.237.171.78/M04545a.mov", "id": "M04545a"}], "words": [{"word": "risk", "id": 4021}], "id": 3397}