{"unusual": false, "description": "Stora l\u00e5ngfingret, upp\u00e5triktat och v\u00e4nsterv\u00e4nt, kontakt med sprethanden, upp\u00e5triktad och h\u00f6gerv\u00e4nd //\rStora l\u00e5ngfingret (andra handen), upp\u00e5triktat och h\u00f6gerv\u00e4nt, kontakt med sprethanden, upp\u00e5triktad och v\u00e4nsterv\u00e4nd //\rStora nyphanden, upp\u00e5triktad och v\u00e4nsterv\u00e4nd, f\u00f6rs ned\u00e5t ett par g\u00e5nger", "video_url": "http://130.237.171.78/T06994.mov", "versions": [], "deleted": false, "tags": [{"tag": "Kalender - helger och h\u00f6gtider", "id": 29}, {"tag": "P\u00e5sk / Pingst", "id": 46}], "updated_at": "2012-03-15T23:00:00Z", "snapshots": [], "ref_id": "6994", "examples": [], "words": [{"word": "l\u00e5ngfredag", "id": 5867}], "id": 5159}