{"unusual": false, "description": "Bokstaveras", "video_url": "http://130.237.171.78/T08802.mov", "versions": [], "deleted": false, "tags": [{"tag": "Sjukv\u00e5rd", "id": 21}], "updated_at": "2012-03-15T23:00:00Z", "snapshots": [], "ref_id": "8802", "examples": [{"description": "A: I dag \u00e4r det allt fler barn som f\u00e5r diagnosen ADHD j\u00e4mf\u00f6rt med tidigare.", "video_url": "http://130.237.171.78/M08802a.mov", "id": "M08802a"}, {"description": "B: Om man har ADHD har man sv\u00e5rt att koncentrera sig.", "video_url": "http://130.237.171.78/M08802b.mov", "id": "M08802b"}], "words": [{"word": "ADHD", "id": 6396}], "id": 5655}