{"unusual": false, "description": "V-handen, upp\u00e5triktad och in\u00e5tv\u00e4nd, f\u00f6rs kort \u00e5t h\u00f6ger samtidigt som den f\u00f6r\u00e4ndras till L-handen", "video_url": "http://130.237.171.78/T11905.mov", "versions": [], "deleted": false, "tags": [{"tag": "Siffror - grundtal", "id": 35}], "updated_at": "2012-03-15T23:00:00Z", "snapshots": [], "ref_id": "11905", "examples": [{"description": "A: James har nyligen kommit ut ur f\u00e4ngelset d\u00e4r han satt i tjugosju \u00e5r.", "video_url": "http://130.237.171.78/M11905a.mov", "id": "M11905a"}, {"description": "B: Jag har varit p\u00e5 tjugosju olika anst\u00e4llningsintervjuer utan att lyckas f\u00e5 n\u00e5got jobb.", "video_url": "http://130.237.171.78/M11905b.mov", "id": "M11905b"}], "words": [{"word": "tjugosju", "id": 7333}, {"word": "27", "id": 7334}], "id": 6506}