{"unusual": false, "description": "Dubbelkroken, fram\u00e5triktad och ned\u00e5tv\u00e4nd, kontakt ovanp\u00e5 flata handen, h\u00f6gerriktad och upp\u00e5tv\u00e4nd, f\u00f6rs \u00e5t h\u00f6ger i en upp\u00e5tg\u00e5ende b\u00e5ge.", "video_url": "http://130.237.171.78/T00874.mov", "versions": [{"description": "V-handen, ned\u00e5triktad och in\u00e5tv\u00e4nd, kontakt ovanp\u00e5 flata handen, h\u00f6gerriktad och upp\u00e5tv\u00e4nd, f\u00f6rs \u00e5t h\u00f6ger i en upp\u00e5tg\u00e5ende b\u00e5ge.", "video_url": "http://130.237.171.78/V00874a.mov", "id": "V00874a"}], "deleted": false, "tags": [], "updated_at": "2012-03-15T23:00:00Z", "snapshots": [], "ref_id": "874", "examples": [], "words": [{"word": "avg\u00e5", "id": 7726}], "id": 6863}