{"unusual": false, "description": "Spreth\u00e4nder, riktade mot varandra och in\u00e5tv\u00e4nda, f\u00f6rs ned\u00e5t med bibeh\u00e5llen kontakt med br\u00f6stet, upprepas", "video_url": "http://130.237.171.78/T00954.mov", "versions": [{"description": "Spreth\u00e4nder, riktade mot varandra och upp\u00e5tv\u00e4nda, f\u00f6rs ned\u00e5t med bibeh\u00e5llen kontakt med br\u00f6stet, upprepas", "video_url": "http://130.237.171.78/V00954a.mov", "id": "V00954a"}], "deleted": false, "tags": [{"tag": "Kl\u00e4der", "id": 2}], "updated_at": "2013-10-19T02:00:46Z", "snapshots": [], "ref_id": "954", "examples": [{"description": "Egentligen har jag massor av kl\u00e4der men jag anv\u00e4nder bara h\u00e4lften av dem.", "video_url": "http://130.237.171.78/M00954a.mov", "id": "M00954a"}], "words": [{"word": "kl\u00e4der", "id": 98634}], "id": 87771}