{"unusual": false, "description": "Klohanden, v\u00e4nsterriktad och in\u00e5tv\u00e4nd, f\u00f6rs \u00e5t h\u00f6ger framf\u00f6r pannan.\r", "video_url": "http://130.237.171.78/T01489.mov", "versions": [], "deleted": false, "tags": [{"tag": "Yrken", "id": 11}], "updated_at": "2013-10-19T02:00:52Z", "snapshots": [], "ref_id": "1489", "examples": [{"description": "Jag \u00e4r uppvuxen p\u00e5 en bondg\u00e5rd s\u00e5 n\u00e4r jag flyttade hit till Stockholm var jag v\u00e4ldigt ovan vid det h\u00f6ga tempot \r", "video_url": "http://130.237.171.78/M01489a.mov", "id": "M01489a"}], "words": [{"word": "bonde", "id": 99102}], "id": 88166}