{"unusual": false, "description": "Krokfingret, upp\u00e5triktat och v\u00e4nsterv\u00e4nt, f\u00f6rs \u00e5t v\u00e4nster, kontakt bredvid flata handen, upp\u00e5triktad och h\u00f6gerv\u00e4nd, f\u00f6rs slutligen \u00e5t h\u00f6ger", "video_url": "http://130.237.171.78/T03555.mov", "versions": [], "deleted": false, "tags": [{"tag": "Kalender - dygn", "id": 23}], "updated_at": "2013-10-19T02:01:15Z", "snapshots": [], "ref_id": "3555", "examples": [{"description": "3600 sekunder \u00e4r lika med en timme.", "video_url": "http://130.237.171.78/M03555a.mov", "id": "M03555a"}, {"description": "Det \u00e4r n\u00e5gra sekunder kvar tills matchen b\u00f6rjar.", "video_url": "http://130.237.171.78/M03555b.mov", "id": "M03555b"}], "words": [{"word": "sekund", "id": 100726}], "id": 89581}