{"unusual": false, "description": "H\u00e5llh\u00e4nder, fram\u00e5triktade och upp\u00e5tv\u00e4nda, f\u00f6rs fram och tillbaka v\u00e4xelvis", "video_url": "http://130.237.171.78/T03908.mov", "versions": [{"description": "H\u00e5llh\u00e4nder, fram\u00e5triktade och v\u00e4nda mot varamdra, f\u00f6rs fram och tillbaka v\u00e4xelvis", "video_url": "http://130.237.171.78/V03908a.mov", "id": "V03908a"}], "deleted": false, "tags": [{"tag": "Yrken", "id": 11}], "updated_at": "2013-10-19T02:01:18Z", "snapshots": [], "ref_id": "3908", "examples": [], "words": [{"word": "regiss\u00f6r", "id": 101000}], "id": 89828}