{"unusual": false, "description": "Dubbelkroken, upp\u00e5triktad och in\u00e5tv\u00e4nd, f\u00f6rs in\u00e5t mot n\u00e4san", "video_url": "http://130.237.171.78/T04378.mov", "versions": [], "deleted": false, "tags": [], "updated_at": "2013-10-19T02:01:23Z", "snapshots": [], "ref_id": "4378", "examples": [{"description": "\u00c4r du blind? Glaset st\u00e5r ju d\u00e4r.", "video_url": "http://130.237.171.78/M04378a.mov", "id": "M04378a"}], "words": [{"word": "blind", "id": 101380}], "id": 90148}