{"unusual": false, "description": "Flata h\u00e4nder, fram\u00e5triktade och upp\u00e5tv\u00e4nda, f\u00f6rs mot varandra till kontakt bredvid varandra //\rFlata handen, fram\u00e5triktad och ned\u00e5tv\u00e4nd, f\u00f6rs \u00e5t h\u00f6ger med korta upprepade ned\u00e5tr\u00f6relser", "video_url": "http://130.237.171.78/T05273.mov", "versions": [], "deleted": false, "tags": [{"tag": "Skola", "id": 10}], "updated_at": "2013-10-19T02:01:31Z", "snapshots": [], "ref_id": "5273", "examples": [], "words": [{"word": "skolbarn", "id": 101880}], "id": 90602}