{"unusual": false, "description": "Flata h\u00e4nder, fram\u00e5triktade och v\u00e4nda mot varandra, f\u00f6rs upp\u00e5t med upprepande kontakter //\rH\u00e5llh\u00e4nder, upp\u00e5triktade och in\u00e5tv\u00e4nda, f\u00f6rs ned\u00e5t och fr\u00e5n varandra i sm\u00e5 in\u00e5tg\u00e5ende cirklar", "video_url": "http://130.237.171.78/T06835.mov", "versions": [], "deleted": false, "tags": [{"tag": "Religion", "id": 1}], "updated_at": "2013-10-19T02:01:49Z", "snapshots": [], "ref_id": "6835", "examples": [], "words": [{"word": "halleluja", "id": 103181}], "id": 91852}