{"unusual": false, "description": "Flata h\u00e4nder, fram\u00e5triktade och ned\u00e5tv\u00e4nda, vinkelkontakt, f\u00f6rs ned och fr\u00e5n varandra, vrids mot varandra, f\u00f6rs slutligen ned\u00e5t //\rPekfingret, v\u00e4nsterriktat och ned\u00e5tv\u00e4nt, kontakt med \u00f6rat //\rPekfingret, fram\u00e5triktat och ned\u00e5tv\u00e4nt, sl\u00e5s ned\u00e5t ett par g\u00e5nger", "video_url": "http://130.237.171.78/T06881.mov", "versions": [], "deleted": false, "tags": [{"tag": "Religion", "id": 1}], "updated_at": "2013-10-19T02:01:49Z", "snapshots": [], "ref_id": "6881", "examples": [], "words": [{"word": "husf\u00f6rh\u00f6r", "id": 103227}], "id": 91898}