{"unusual": false, "description": "Pekfingret, fram\u00e5triktat och v\u00e4nsterv\u00e4nt, bakom stillast\u00e5ende flata handen, h\u00f6gerriktad och upp\u00e5tv\u00e4nd, pekfingret f\u00f6r\u00e4ndras till krokfinger ett par g\u00e5nger //\rFlata h\u00e4nder, fram\u00e5triktade och ned\u00e5tv\u00e4nda, vinkelkontakt, f\u00f6rs f\u00f6rst fr\u00e5n varandra, sedan ned\u00e5t samtidigt som de vrids mot varandra", "video_url": "http://130.237.171.78/T07190.mov", "versions": [], "deleted": false, "tags": [{"tag": "Religion", "id": 1}], "updated_at": "2013-10-19T02:01:53Z", "snapshots": [], "ref_id": "7190", "examples": [], "words": [{"word": "vapenhus", "id": 103536}], "id": 92203}