{"unusual": false, "description": "Bokstaveras", "video_url": "http://130.237.171.78/T08771.mov", "versions": [], "deleted": false, "tags": [{"tag": "Spel / Kortspel", "id": 7}], "updated_at": "2013-10-19T02:02:05Z", "snapshots": [], "ref_id": "8771", "examples": [{"description": "Jag sk\u00e4ms f\u00f6r att jag inte vet hur man spelar poker. Alla andra kan men inte jag.", "video_url": "http://130.237.171.78/M08771a.mov", "id": "M08771a"}], "words": [{"word": "poker", "id": 103838}], "id": 92481}