{"unusual": false, "description": "Tumhanden, upp\u00e5triktad och v\u00e4nsterv\u00e4nd, upprepade kontakter med hakan", "video_url": "http://130.237.171.78/T09659.mov", "versions": [{"description": "Flyghanden, upp\u00e5triktad och v\u00e4nsterv\u00e4nd, upprepade kontakter med hakan", "video_url": "http://130.237.171.78/V09659a.mov", "id": "V09659a"}], "deleted": false, "tags": [{"tag": "Mat & Dryck", "id": 17}, {"tag": "Mat & Dryck - Drycker", "id": 73}], "updated_at": "2013-10-19T02:02:09Z", "snapshots": [], "ref_id": "9659", "examples": [], "words": [{"word": "alkohol", "id": 104133}], "id": 92756}