{"unusual": false, "description": "Flata handen, fram\u00e5triktad och ned\u00e5tv\u00e4nd, f\u00f6rs \u00e5t h\u00f6ger med upprepade korta ned\u00e5tr\u00f6relser //\rDubbelkroken, fram\u00e5triktad och ned\u00e5tv\u00e4nd, f\u00f6rs \u00e5t v\u00e4nster och h\u00f6ger med medial kontakt ovanp\u00e5 knutna handen. h\u00f6gerriktad och in\u00e5tv\u00e4nd", "video_url": "http://130.237.171.78/T10513.mov", "versions": [], "deleted": false, "tags": [], "updated_at": "2013-10-19T02:02:14Z", "snapshots": [], "ref_id": "10513", "examples": [], "words": [{"word": "barnvakt", "id": 104447}], "id": 93047}