{"unusual": false, "description": "Klohanden, fram\u00e5triktad och ned\u00e5tv\u00e4nd, f\u00f6rs ned\u00e5t ovanp\u00e5 pekfingret, upp\u00e5triktat och in\u00e5tv\u00e4nt", "video_url": "http://130.237.171.78/T12364.mov", "versions": [{"description": "Klohanden, fram\u00e5triktad och ned\u00e5tv\u00e4nd, f\u00f6rs ned\u00e5t ovanp\u00e5 pekfingret, upp\u00e5triktat och in\u00e5tv\u00e4nt", "video_url": "http://130.237.171.78/V12364a.mov", "id": "V12364a"}], "deleted": false, "tags": [{"tag": "Idrott / Motion", "id": 21}, {"tag": "Hobby", "id": 50}], "updated_at": "2013-10-19T02:02:25Z", "snapshots": [], "ref_id": "12364", "examples": [], "words": [{"word": "fallsk\u00e4rm", "id": 105196}], "id": 93710}