{"unusual": false, "description": "B\u00f6jda 4-handen, fram\u00e5triktad och v\u00e4nsterv\u00e4nd, kontakt bredvid flata handen, fram\u00e5triktad och h\u00f6gerv\u00e4nd, b\u00e5da h\u00e4nder f\u00f6rs \u00e5t h\u00f6ger samtidigt som den vrids upp\u00e5t, upprepas", "video_url": "http://130.237.171.78/T01409.mov", "versions": [], "deleted": false, "tags": [{"tag": "Siffror - veckor", "id": 59}], "updated_at": "2013-10-19T02:00:51Z", "snapshots": [], "ref_id": "1409", "examples": [{"description": "I min fastighet finns ett soprum som brukar t\u00f6mmas var fj\u00e4rde vecka.", "video_url": "http://130.237.171.78/M01409a.mov", "id": "M01409a"}], "words": [{"word": "var fj\u00e4rde vecka", "id": 106367}], "id": 94778}