{"unusual": false, "description": "Tumhanden, v\u00e4nsterriktad och in\u00e5tv\u00e4nd, upprepade kontakter med hakan //\rBokstaveras: I-S-T", "video_url": "http://130.237.171.78/T08369.mov", "versions": [], "deleted": false, "tags": [], "updated_at": "2013-10-19T02:02:03Z", "snapshots": [], "ref_id": "8369", "examples": [{"description": "Alkoholister f\u00f6rnekar ofta att de har problem.\r", "video_url": "http://130.237.171.78/M04493a.mov", "id": "M04493a"}], "words": [{"word": "alkoholist", "id": 107410}], "id": 95688}