{"unusual": false, "description": "B\u00f6jda tupphanden, upp\u00e5triktad och v\u00e4nsterv\u00e4nd, f\u00f6rs ned till kontakt ovanp\u00e5 flata handen, h\u00f6gerriktad och upp\u00e5tv\u00e4nd, f\u00f6rs slutligen upp\u00e5t //\rVinkelh\u00e4nder, fram\u00e5triktade och ned\u00e5tv\u00e4nda, kontakt bredvid varandra, f\u00f6rs sedan ned\u00e5t fr\u00e5n varandra i ut\u00e5tg\u00e5ende b\u00e5ge samtidigt som de vrids upp\u00e5t, kontakt bredvid varandra", "video_url": "http://130.237.171.78/T04879.mov", "versions": [], "deleted": false, "tags": [{"tag": "Lek", "id": 25}], "updated_at": "2013-10-16T22:00:00Z", "snapshots": [], "ref_id": "4879", "examples": [], "words": [{"word": "studsboll", "id": 107523}], "id": 95783}