{"unusual": false, "description": "Flata h\u00e4nder, fram\u00e5triktade och upp\u00e5tv\u00e4nda, f\u00f6rs ned\u00e5t samtidigt som de vrids ned\u00e5t", "video_url": "http://130.237.171.78/T05284.mov", "versions": [], "deleted": false, "tags": [], "updated_at": "2013-10-16T22:00:00Z", "snapshots": [], "ref_id": "5284", "examples": [{"description": "P\u00e5 m\u00f6tet kunde vi inte komma n\u00e5gon vart utan vi bordlade \u00e4rendet.", "video_url": "http://130.237.171.78/M00634a.mov", "id": "M00634a"}, {"description": "P\u00e5 m\u00f6tet kunde vi inte komma n\u00e5gon vart utan vi bordlade \u00e4rendet till ett senare tillf\u00e4lle.", "video_url": "http://130.237.171.78/M00634b.mov", "id": "M00634b"}], "words": [{"word": "bordl\u00e4gga", "id": 107668}], "id": 95901}