{"unusual": false, "description": "H\u00e5llhanden, in\u00e5triktad och h\u00f6gerv\u00e4nd, f\u00f6rs upp och ned med bibeh\u00e5llen kontakt med br\u00f6stet samtidigt som den andra handen h\u00e5lles stilla i kontakt med br\u00f6stet", "video_url": "http://130.237.171.78/T08115.mov", "versions": [], "deleted": false, "tags": [{"tag": "Kl\u00e4der", "id": 2}], "updated_at": "2013-10-20T22:00:00Z", "snapshots": [], "ref_id": "8115", "examples": [], "words": [{"word": "blixtl\u00e5s", "id": 108178}], "id": 96344}