{"unusual": false, "description": "Nyphanden, upp\u00e5triktad och in\u00e5tv\u00e4nd, f\u00f6rs ned\u00e5t samtidigt som den sl\u00e5s \u00e5t v\u00e4nster (med bibeh\u00e5llen kontakt) bakom flata handen, h\u00f6gerriktad och in\u00e5tv\u00e4nd", "video_url": "http://130.237.171.78/T09055.mov", "versions": [], "deleted": false, "tags": [], "updated_at": "2013-10-24T22:00:00Z", "snapshots": [], "ref_id": "9055", "examples": [], "words": [{"word": "rita", "id": 108396}, {"word": "ritning", "id": 108397}], "id": 96537}